gamgee/__init__.py
gamgee/args.py
gamgee/auth.py
gamgee/errors.py
gamgee/parsers.py
gamgee/types.py
gamgee-0.3.3.dist-info/LICENSE
gamgee-0.3.3.dist-info/METADATA
gamgee-0.3.3.dist-info/WHEEL
gamgee-0.3.3.dist-info/top_level.txt
gamgee-0.3.3.dist-info/RECORD
