Metadata-Version: 2.1
Name: gamgee
Version: 0.3.3
Summary: Gamgee helps you get up and running quickly with an AWS Lambda API.
Home-page: https://github.com/a-poor/gamgee
Author: Austin Poor
Author-email: 45295232+a-poor@users.noreply.github.com
License: UNKNOWN
Platform: UNKNOWN
Classifier: Programming Language :: Python :: 3
Classifier: License :: OSI Approved :: MIT License
Classifier: Operating System :: OS Independent
Requires-Python: >=3.7
License-File: LICENSE
Requires-Dist: PyJWT (==2.1.0)
Requires-Dist: pydantic (==1.8.2)
